LICENSE.txt
MANIFEST.in
NOTICE
README.md
setup.py
logalyzer/__init__.py
logalyzer/database.py
logalyzer/gui.py
logalyzer/logread.py
logalyzer/main.py
logalyzer/parse.py
logalyzer/records.py
logalyzer/sift.py
logalyzer/util.py
logalyzer/writer.py
logalyzer.egg-info/PKG-INFO
logalyzer.egg-info/SOURCES.txt
logalyzer.egg-info/dependency_links.txt
logalyzer.egg-info/entry_points.txt
logalyzer.egg-info/requires.txt
logalyzer.egg-info/top_level.txt
logalyzer/rules/README.txt
logalyzer/rules/blocked.ip
logalyzer/rules/bots.ua
logalyzer/rules/china.net
logalyzer/rules/hackers.ip
logalyzer/rules/hackers.url
logalyzer/rules/logspam.ref
logalyzer/test/__init__.py
logalyzer/test/test_database.py
logalyzer/test/test_gui.py
logalyzer/test/test_logread.py
logalyzer/test/test_parse.py
logalyzer/test/test_records.py
logalyzer/test/test_sift.py
logalyzer/test/testbase.py
sql-examples/duplicate-entries.sql
sql-examples/entries.sql
sql-examples/images-current-month.sql
sql-examples/images.sql
sql-examples/multiple-hits-per-month-foreach-url.sql
sql-examples/numeric-vhost.sql
sql-examples/recent-entries.sql
sql-examples/recent-hits.sql
sql-examples/recent-html-hits.sql
sql-examples/referrer-on-image.sql
sql-examples/referrer.sql
sql-examples/suspiciously-prolific-visitors.sql
sql-examples/ua-with-suspiciously-many-404.sql
sql-examples/unique-ip-on-vhost.sql
sql-examples/unique-visitors-by-url-recent.sql
sql-examples/unique-visitors-recent.sql
sql-examples/uniques-on-image.sql
sql-examples/urls-on-404.sql