Metadata-Version: 1.2
Name: logalyzer
Version: 0.4
Summary: Web server HTTP access log parsing, filtering, and SQL database storage.
Home-page: http://edsuom.com/logalyzer.html
Author: Edwin A. Suominen
Author-email: foss@edsuom.com
Maintainer: Edwin A. Suominen
Maintainer-email: foss@edsuom.com
License: Apache License (2.0)
Project-URL: API, http://edsuom.com/logalyzer/logalyzer.html
Project-URL: GitHub, https://github.com/edsuom/logalyzer
Keywords: twisted,asynchronous,async,log,logfile,analysis,database,filtering,web,access log
Platform: OS Independent
Classifier: Development Status :: 4 - Beta
Classifier: Framework :: Twisted
Classifier: Intended Audience :: Information Technology
Classifier: Intended Audience :: System Administrators
Classifier: License :: OSI Approved :: Apache Software License
Classifier: Operating System :: OS Independent
Classifier: Programming Language :: Python :: 2.7
Classifier: Programming Language :: Python :: 2 :: Only
Classifier: Programming Language :: SQL
Classifier: Topic :: Database
Classifier: Topic :: Internet :: Log Analysis
Classifier: Topic :: System :: Systems Administration
